pyplattsapi/__init__.py
pyplattsapi/global_oil_demand.py
pyplattsapi/locationmap.py
pyplattsapi/oil_inventory.py
pyplattsapi/plattsapicore.py
pyplattsapi/price_forecast.py
pyplattsapi/refining_margins_crude_arbitrage.py
pyplattsapi/world_oil_supply.py
pyplattsapi/world_refinery_database.py
tests/__init__.py
tests/test_global_oil_demand.py
tests/test_plattsapicore.py
tests/test_refining_margins_crude_arbitrage.py
tests/test_world_oil_supply.py
tests/test_world_refinery_database.py
pyplattsapi-0.0.12.dist-info/METADATA
pyplattsapi-0.0.12.dist-info/WHEEL
pyplattsapi-0.0.12.dist-info/top_level.txt
pyplattsapi-0.0.12.dist-info/RECORD
