Metadata-Version: 2.1
Name: pyplattsapi
Version: 0.0.12
Summary: Wrapper around Platts API
Home-page: https://github.com/aeorxc/pyplattsapi
Author: aeorxc
License: UNKNOWN
Project-URL: Source, https://github.com/aeorxc/pyplattsapi
Platform: UNKNOWN
Classifier: Programming Language :: Python :: 3
Classifier: License :: OSI Approved :: MIT License
Classifier: Operating System :: OS Independent
Requires-Python: >=3.8
Requires-Dist: pandas
Requires-Dist: requests
Requires-Dist: cachetools
